pyosplus/__init__.py
pyosplus/pyosplus.py
pyosplus-1.3.0.dist-info/METADATA
pyosplus-1.3.0.dist-info/WHEEL
pyosplus-1.3.0.dist-info/licenses/LICENSE
pyosplus-1.3.0.dist-info/RECORD
