Metadata-Version: 2.1
Name: pyosplus
Version: 1.3.0
Summary: useful Python package based on os/os.path
Project-URL: Homepage, https://github.com/crazytexer/pyosplus
Project-URL: Bug Tracker, https://github.com/crazytexer/pyosplus/issues
Author: Evgenii Shirokov
License-File: LICENSE
Classifier: License :: OSI Approved :: MIT License
Classifier: Operating System :: OS Independent
Classifier: Programming Language :: Python :: 3
Requires-Python: >=3.10
